logicore_django_react/__init__.py
logicore_django_react/commons.py
logicore_django_react/models.py
logicore_django_react/urls.py
logicore_django_react/views.py
logicore_django_react/templates/logicore_django_react/home.html
logicore_django_react/templates/logicore_django_react/include_react_css.html
logicore_django_react/templates/logicore_django_react/include_react_js.html
logicore_django_react/templatetags/react_tags.py
logicore_django_react/templatetags/react_tags_dev.py
logicore_django_react-1.0.0.dev23.dist-info/LICENSE
logicore_django_react-1.0.0.dev23.dist-info/METADATA
logicore_django_react-1.0.0.dev23.dist-info/WHEEL
logicore_django_react-1.0.0.dev23.dist-info/top_level.txt
logicore_django_react-1.0.0.dev23.dist-info/RECORD
