Metadata-Version: 2.1
Name: logicore-django-react
Version: 1.0.0.dev23
Summary: A little Python module helping to use Django and React on a single port during development and production
Author-email: Andrei Boltachev <andrewboltachev@gmail.com>
License: Copyright (c) 2012-2022 Scott Chacon and others
Project-URL: Homepage, https://github.com/Logicore-project/logicore-django-react
Project-URL: Bug Tracker, https://github.com/Logicore-project/logicore-django-react/issues
Classifier: Programming Language :: Python :: 3
Classifier: License :: OSI Approved :: MIT License
Classifier: Operating System :: OS Independent
Requires-Python: >=3.7
License-File: LICENSE
Requires-Dist: Django <6
Requires-Dist: django-proxy ==1.2.2
